Svnbook15FinalZh/README.md
Svnbook15FinalZh/__init__.py
Svnbook15FinalZh/__main__.py
Svnbook15FinalZh/file.pdf
Svnbook15FinalZh/index.html
svnbook_1_5_final_zh-2024.3.2.0.dist-info/METADATA
svnbook_1_5_final_zh-2024.3.2.0.dist-info/WHEEL
svnbook_1_5_final_zh-2024.3.2.0.dist-info/entry_points.txt
svnbook_1_5_final_zh-2024.3.2.0.dist-info/top_level.txt
svnbook_1_5_final_zh-2024.3.2.0.dist-info/RECORD
